{
  "name": "Teste EJC",
  "short_name": "Teste",
  "start_url": "./AdmEJC.html",
  "display": "standalone",
  "background_color": "#ffffff",
  "theme_color": "#2196f3",
  "prefer_related_applications": false,
  "icons": [
    {
      "src": "https://cdn-icons-png.flaticon.com/512/25/25231.png",
      "sizes": "512x512",
      "type": "image/png",
      "purpose": "any"
    },
    {
      "src": "https://cdn-icons-png.flaticon.com/512/25/25231.png",
      "sizes": "512x512",
      "type": "image/png",
      "purpose": "maskable"
    }
  ]
}
